mitsubishi_echonet/__init__.py
mitsubishi_echonet/eojx.py
mitsubishi_echonet/epc.py
mitsubishi_echonet/esv.py
mitsubishi_echonet/functions.py
mitsubishi_echonet-0.5.1.dist-info/LICENCE.txt
mitsubishi_echonet-0.5.1.dist-info/METADATA
mitsubishi_echonet-0.5.1.dist-info/WHEEL
mitsubishi_echonet-0.5.1.dist-info/top_level.txt
mitsubishi_echonet-0.5.1.dist-info/RECORD
