Metadata-Version: 2.1
Name: mitsubishi-echonet
Version: 0.5.1
Summary: A library for interfacing with Mitsubishi HVAC via the Echonet lite protocol.
Home-page: http://pypi.python.org/pypi/mitsubishi_echonet/
Author: Scott Phillips
License: LICENSE.txt
Platform: UNKNOWN
